{"name":"CrossSectionalMeanReversion_5D_USEquities","universe_definition":["US listed common stocks","Primary listings only","Market cap > $500M","Median daily dollar volume > $5M over past 60 trading days","Price > $5","Exclude ADRs, ETFs, closed-end funds, SPACs, warrants, preferreds","Exclude stocks with less than 252 trading days of history","Top 1000 names by liquidity after filters"],"data_requirements":["Daily OHLCV","Adjusted close and corporate actions","Shares outstanding or free-float market cap","Sector and industry classification","Delisting returns","Borrow availability proxy if shorting","Trading calendar and symbol mapping"],"signal_definition":["Compute 5-day residual return versus sector-neutral cross-sectional model","Rank stocks cross-sectionally each rebalance date","Go long bottom decile of ranked residual returns","Go short top decile of ranked residual returns","Size positions by inverse volatility and normalized signal strength","Neutralize beta and sector exposures at portfolio construction"],"holding_period":"5 trading days with overlapping portfolios","rebalancing_rule":["Rebalance daily at close","Enter new tranche each day","Exit each tranche after 5 trading days","Skip names failing liquidity or price filters on entry date"],"transaction_cost_model":["Commission: 0.5 bps per side","Slippage: max(5 bps, 0.1 * daily volatility * participation rate)","Borrow cost on shorts: 25 bps annualized baseline","Market impact scaled by ADV participation","Apply one-day execution delay in robustness tests"],"risk_model":["Estimate daily volatility using 60-day exponential window","Constrain portfolio beta to market near zero","Constrain sector exposures to near zero","Single-name weight capped by liquidity and volatility","Monitor gross, net, factor, and idiosyncratic risk"],"constraints":["Dollar neutral","Gross exposure <= 200%","Net exposure within +/- 5%","Max single-name absolute weight 1.5%","Max sector active weight 3%","Max daily traded notional per name <= 10% of ADV","Minimum 50 longs and 50 shorts","No position in halted or missing-data names"],"hyperparameters":["Residual lookback: 5 days","Volatility lookback: 60 days","Liquidity lookback: 60 days","Signal winsorization: 2.5 standard deviations","Long bucket: bottom 10%","Short bucket: top 10%","Holding period: 5 days","Beta neutralization target: 0","Sector neutralization: GICS sector"],"validation_plan":["In-sample period: 2012-2019","Out-of-sample period: 2020-2025","Walk-forward re-estimation annually","Evaluate with and without transaction costs","Run subperiod tests by regime and volatility state","Bootstrap trade-level and month-level performance","Check sensitivity to bucket size, holding period, and delay","Use delisting-aware survivorship-free data"],"failure_modes":["Signal decay after costs","Performance concentrated in few periods or sectors","Hidden exposure to size, value, or short-term reversal crowding","Liquidity stress during market shocks","Short borrow unavailability or elevated borrow fees","Backtest bias from survivorship, lookahead, or stale fundamentals","Execution slippage materially above model"],"minimum_acceptance_criteria":["Out-of-sample Sharpe >= 1.25 net of costs","Annualized return >= 8% net","Max drawdown <= 15%","Average daily turnover <= 35% of gross exposure","Positive returns in at least 60% of rolling 12-month windows","Stable performance across top-level sectors and market regimes","No single year contributes more than 35% of total PnL"]}
